django_cowhite_contact_us/__init__.py
django_cowhite_contact_us/admin.py
django_cowhite_contact_us/apps.py
django_cowhite_contact_us/forms.py
django_cowhite_contact_us/models.py
django_cowhite_contact_us/tests.py
django_cowhite_contact_us/urls.py
django_cowhite_contact_us/views.py
django_cowhite_contact_us/management/__init__.py
django_cowhite_contact_us/management/commands/__init__.py
django_cowhite_contact_us/management/commands/send_contact_mails.py
django_cowhite_contact_us/migrations/0001_initial.py
django_cowhite_contact_us/migrations/__init__.py
django_cowhite_contact_us/static/django_cowhite_contact_us/fonts/Roboto/LICENSE.txt
django_cowhite_contact_us/static/django_cowhite_contact_us/fonts/Roboto/Roboto-Black.ttf
django_cowhite_contact_us/static/django_cowhite_contact_us/fonts/Roboto/Roboto-BlackItalic.ttf
django_cowhite_contact_us/static/django_cowhite_contact_us/fonts/Roboto/Roboto-Bold.ttf
django_cowhite_contact_us/static/django_cowhite_contact_us/fonts/Roboto/Roboto-BoldItalic.ttf
django_cowhite_contact_us/static/django_cowhite_contact_us/fonts/Roboto/Roboto-Italic.ttf
django_cowhite_contact_us/static/django_cowhite_contact_us/fonts/Roboto/Roboto-Light.ttf
django_cowhite_contact_us/static/django_cowhite_contact_us/fonts/Roboto/Roboto-LightItalic.ttf
django_cowhite_contact_us/static/django_cowhite_contact_us/fonts/Roboto/Roboto-Medium.ttf
django_cowhite_contact_us/static/django_cowhite_contact_us/fonts/Roboto/Roboto-MediumItalic.ttf
django_cowhite_contact_us/static/django_cowhite_contact_us/fonts/Roboto/Roboto-Regular.ttf
django_cowhite_contact_us/static/django_cowhite_contact_us/fonts/Roboto/Roboto-Thin.ttf
django_cowhite_contact_us/static/django_cowhite_contact_us/fonts/Roboto/Roboto-ThinItalic.ttf
django_cowhite_contact_us/static/django_cowhite_contact_us/lib/bootstrap-3.3.7-dist/css/bootstrap.min.css
django_cowhite_contact_us/static/django_cowhite_contact_us/lib/bootstrap-3.3.7-dist/css/bootstrap.min.css.map
django_cowhite_contact_us-0.1.2.dist-info/METADATA
django_cowhite_contact_us-0.1.2.dist-info/RECORD
django_cowhite_contact_us-0.1.2.dist-info/WHEEL
django_cowhite_contact_us-0.1.2.dist-info/top_level.txt
